vc_investor_scraper-1.0.0.dist-info/licenses/LICENSE
vcsheet_scraper/__init__.py
vcsheet_scraper/scraper.py
vc_investor_scraper-1.0.0.dist-info/METADATA
vc_investor_scraper-1.0.0.dist-info/WHEEL
vc_investor_scraper-1.0.0.dist-info/entry_points.txt
vc_investor_scraper-1.0.0.dist-info/top_level.txt
vc_investor_scraper-1.0.0.dist-info/RECORD
