Metadata-Version: 2.4
Name: vc-investor-scraper
Version: 1.0.0
Summary: A powerful Python tool to scrape VC investor data from VCSheet.com with Odoo CRM integration
Home-page: https://github.com/antonpavlenko/vc-investor-scraper
Author: Anton Pavlenko
Author-email: Anton Pavlenko <apavlenko@hmcorp.fund>
License: MIT License
Project-URL: Homepage, https://github.com/antonpavlenko/vc-investor-scraper
Project-URL: Documentation, https://github.com/antonpavlenko/vc-investor-scraper#readme
Project-URL: Repository, https://github.com/antonpavlenko/vc-investor-scraper
Project-URL: Bug Reports, https://github.com/antonpavlenko/vc-investor-scraper/issues
Keywords: vc,venture capital,investors,scraper,odoo,crm,vcsheet,fintech,startup
Classifier: Development Status :: 5 - Production/Stable
Classifier: Intended Audience :: Developers
Classifier: Intended Audience :: Financial and Insurance Industry
Classifier: Topic :: Office/Business :: Financial :: Investment
Classifier: Topic :: Internet :: WWW/HTTP :: Dynamic Content
Classifier: Topic :: Software Development :: Libraries :: Python Modules
Classifier: License :: OSI Approved :: MIT License
Classifier: Programming Language :: Python :: 3
Classifier: Programming Language :: Python :: 3.7
Classifier: Programming Language :: Python :: 3.8
Classifier: Programming Language :: Python :: 3.9
Classifier: Programming Language :: Python :: 3.10
Classifier: Programming Language :: Python :: 3.11
Classifier: Programming Language :: Python :: 3.12
Classifier: Operating System :: OS Independent
Requires-Python: >=3.7
License-File: LICENSE
Requires-Dist: requests>=2.25.0
Requires-Dist: beautifulsoup4>=4.9.0
Requires-Dist: lxml>=4.6.0
Dynamic: author
Dynamic: home-page
Dynamic: license-file
Dynamic: requires-python
